.gitlab-ci.yml
.travis.yml
CHANGES.rst
CONTRIBUTORS.rst
DEVELOP.rst
LICENSE.GPL
LICENSE.rst
MANIFEST.in
README.rst
constraints.txt
constraints_plone52.txt
constraints_plone60.txt
requirements.txt
requirements_plone52.txt
requirements_plone60.txt
setup.cfg
setup.py
tox.ini
docs/conf.py
docs/index.rst
src/cs/__init__.py
src/cs.volto.publiccontracts.egg-info/PKG-INFO
src/cs.volto.publiccontracts.egg-info/SOURCES.txt
src/cs.volto.publiccontracts.egg-info/dependency_links.txt
src/cs.volto.publiccontracts.egg-info/entry_points.txt
src/cs.volto.publiccontracts.egg-info/namespace_packages.txt
src/cs.volto.publiccontracts.egg-info/not-zip-safe
src/cs.volto.publiccontracts.egg-info/requires.txt
src/cs.volto.publiccontracts.egg-info/top_level.txt
src/cs/volto/__init__.py
src/cs/volto/publiccontracts/__init__.py
src/cs/volto/publiccontracts/configure.zcml
src/cs/volto/publiccontracts/interfaces.py
src/cs/volto/publiccontracts/permissions.zcml
src/cs/volto/publiccontracts/setuphandlers.py
src/cs/volto/publiccontracts/testing.py
src/cs/volto/publiccontracts/browser/__init__.py
src/cs/volto/publiccontracts/browser/configure.zcml
src/cs/volto/publiccontracts/browser/import_public_contracts.py
src/cs/volto/publiccontracts/browser/overrides/.gitkeep
src/cs/volto/publiccontracts/browser/static/.gitkeep
src/cs/volto/publiccontracts/content/__init__.py
src/cs/volto/publiccontracts/content/contract.py
src/cs/volto/publiccontracts/content/contract.xml
src/cs/volto/publiccontracts/content/contracts_folder.py
src/cs/volto/publiccontracts/content/contracts_folder.xml
src/cs/volto/publiccontracts/indexers/__init__.py
src/cs/volto/publiccontracts/indexers/configure.zcml
src/cs/volto/publiccontracts/indexers/state_index.py
src/cs/volto/publiccontracts/indexers/state_index.zcml
src/cs/volto/publiccontracts/locales/README.rst
src/cs/volto/publiccontracts/locales/__init__.py
src/cs/volto/publiccontracts/locales/update.py
src/cs/volto/publiccontracts/locales/update.sh
src/cs/volto/publiccontracts/locales/en/LC_MESSAGES/cs.volto.publiccontracts.po
src/cs/volto/publiccontracts/profiles/default/browserlayer.xml
src/cs/volto/publiccontracts/profiles/default/catalog.xml
src/cs/volto/publiccontracts/profiles/default/metadata.xml
src/cs/volto/publiccontracts/profiles/default/rolemap.xml
src/cs/volto/publiccontracts/profiles/default/types.xml
src/cs/volto/publiccontracts/profiles/default/types.xml.example
