Metadata-Version: 2.1
Name: cs.volto.publiccontracts
Version: 1.0
Summary: An add-on for Plone
Home-page: https://github.com/collective/cs.volto.publiccontracts
Author: Lur Ibargutxi
Author-email: libargutxi@codesyntax.com
License: GPL version 2
Project-URL: PyPI, https://pypi.python.org/pypi/cs.volto.publiccontracts
Project-URL: Source, https://github.com/collective/cs.volto.publiccontracts
Project-URL: Tracker, https://github.com/collective/cs.volto.publiccontracts/issues
Keywords: Python Plone CMS
Platform: UNKNOWN
Classifier: Environment :: Web Environment
Classifier: Framework :: Plone
Classifier: Framework :: Plone :: Addon
Classifier: Framework :: Plone :: 5.2
Classifier: Framework :: Plone :: 6.0
Classifier: Programming Language :: Python
Classifier: Programming Language :: Python :: 3.7
Classifier: Programming Language :: Python :: 3.8
Classifier: Programming Language :: Python :: 3.9
Classifier: Operating System :: OS Independent
Classifier: License :: OSI Approved :: GNU General Public License v2 (GPLv2)
Requires-Python: >=3.7
Provides-Extra: test
